<annotation>
	<folder>images - Copy</folder>
	<filename>-HalfCabUnder5Kn-f67b171f-4560-40c1-b78f-c7b17f8d8bae.jpg</filename>
	<path>C:\python\projects\Upwork-Projects\Sara RCNN\YOLO\data\validation\images - Copy\-HalfCabUnder5Kn-f67b171f-4560-40c1-b78f-c7b17f8d8bae.jpg</path>
	<source>
		<database>Unknown</database>
	</source>
	<size>
		<width>800</width>
		<height>600</height>
		<depth>3</depth>
	</size>
	<segmented>0</segmented>
	<object>
		<name>halfcab</name>
		<pose>Unspecified</pose>
		<truncated>0</truncated>
		<difficult>0</difficult>
		<bndbox>
			<xmin>64</xmin>
			<ymin>114</ymin>
			<xmax>480</xmax>
			<ymax>241</ymax>
		</bndbox>
	</object>
	<object>
		<name>registration_numver</name>
		<pose>Unspecified</pose>
		<truncated>0</truncated>
		<difficult>0</difficult>
		<bndbox>
			<xmin>116</xmin>
			<ymin>197</ymin>
			<xmax>147</xmax>
			<ymax>214</ymax>
		</bndbox>
	</object>
	<object>
		<name>human</name>
		<pose>Unspecified</pose>
		<truncated>0</truncated>
		<difficult>0</difficult>
		<bndbox>
			<xmin>311</xmin>
			<ymin>152</ymin>
			<xmax>340</xmax>
			<ymax>190</ymax>
		</bndbox>
	</object>
	<object>
		<name>PDF</name>
		<pose>Unspecified</pose>
		<truncated>0</truncated>
		<difficult>0</difficult>
		<bndbox>
			<xmin>313</xmin>
			<ymin>159</ymin>
			<xmax>346</xmax>
			<ymax>182</ymax>
		</bndbox>
	</object>
	<object>
		<name>human</name>
		<pose>Unspecified</pose>
		<truncated>0</truncated>
		<difficult>0</difficult>
		<bndbox>
			<xmin>350</xmin>
			<ymin>143</ymin>
			<xmax>384</xmax>
			<ymax>189</ymax>
		</bndbox>
	</object>
	<object>
		<name>PWC</name>
		<pose>Unspecified</pose>
		<truncated>0</truncated>
		<difficult>0</difficult>
		<bndbox>
			<xmin>59</xmin>
			<ymin>100</ymin>
			<xmax>189</xmax>
			<ymax>147</ymax>
		</bndbox>
	</object>
	<object>
		<name>human</name>
		<pose>Unspecified</pose>
		<truncated>0</truncated>
		<difficult>0</difficult>
		<bndbox>
			<xmin>111</xmin>
			<ymin>86</ymin>
			<xmax>147</xmax>
			<ymax>120</ymax>
		</bndbox>
	</object>
</annotation>
